crewai_primordia/__init__.py
crewai_primordia/meter.py
crewai_primordia-0.1.0.dist-info/METADATA
crewai_primordia-0.1.0.dist-info/WHEEL
crewai_primordia-0.1.0.dist-info/RECORD
